[{"cmd":"history","msg":"# Displays all previous commands run from this user containing the phrase \"execute\".  Numbers each command.  You can then run one of the commands by typing !number\n$ history | grep -i execute\n675 ./executeShellCommand\n678 ./transferFiles -o LARGE\n$ !678\n#runs ./transferFiles -o LARGE","updated_at":"2016-03-08T10:18:36.000Z","id":143,"up":9,"down":0},{"cmd":"history","msg":"# Show most used commands\nhistory | awk '{a[$2]++}END{for(i in a){print a[i] \" \" i}}' | sort -rn | head","updated_at":"2015-10-06T14:24:18.000Z","id":293,"up":5,"down":0}]