[{"cmd":"rpm","msg":"# RPM Package Manager\n# install a package\nrpm -Uvh package.rpm\n\n# install a package that doesn't have needed dependencies (never do this)\nrpm -Uvh --nodeps --force package.rpm\n\n# List information about an installed package\nrpm -qi package\n\n# List information about a package file\nrpm -qip package.rpm\n\n# Remove a package\nrpm -e package\n\n# Remove a package without checking dependencies (never do this)\nrpm -e --nodeps package\n\n# Search for a package\nrpm -qa |grep package\n\n# Output package information based on package variables\nrpm -q package --qf %{name}-%{version}%{arch}\n\n# List known variables\nrpm --showrc\n\n# What packages does this package require\nrpm -q package --requires\n\n# What capabilities does this package provide\nrpm -q package --provides\n\n# What packages require this package/capability\nrpm -q package --whatrequires\n\n# Install package into another base directory\nrpm --root /some/path -Uvh package.rpm\n\n# Show the scripts (postun,preun,post,pre) in the package\nrpm -q package --scripts\n\n# Rebuild rpm database\nrpm --rebuilddb","updated_at":"2014-12-11T15:59:18.000Z","id":468,"up":5,"down":0},{"cmd":"rpm","msg":"# Lists all the files this package will install\nrpm -ql package","updated_at":"2014-02-18T19:03:47.000Z","id":567,"up":1,"down":0},{"cmd":"rpm","msg":"# your_comment_here\nRPM is a cross-plataform tool by RHEL\n\nrmp [operation] [option] [packages-files|package-names]\n\nexample:\n\nrmp -Uvh samba-3.6.5-86.fc17.1.x86_64.rmp","updated_at":"2014-03-30T12:28:03.000Z","id":414,"up":1,"down":2}]